reportr_backend_client/__init__.py
reportr_backend_client/api_client.py
reportr_backend_client/api_response.py
reportr_backend_client/configuration.py
reportr_backend_client/exceptions.py
reportr_backend_client/py.typed
reportr_backend_client/rest.py
reportr_backend_client/api/__init__.py
reportr_backend_client/api/news_api.py
reportr_backend_client/api/status_api.py
reportr_backend_client/models/__init__.py
reportr_backend_client/models/health.py
reportr_backend_client/models/http_validation_error.py
reportr_backend_client/models/news_item.py
reportr_backend_client/models/news_item_created.py
reportr_backend_client/models/paginated_news_response.py
reportr_backend_client/models/readiness.py
reportr_backend_client/models/time_filter.py
reportr_backend_client/models/validation_error.py
reportr_backend_client/models/validation_error_loc_inner.py
reportr_backend_client-1.0.0.dist-info/METADATA
reportr_backend_client-1.0.0.dist-info/WHEEL
reportr_backend_client-1.0.0.dist-info/top_level.txt
reportr_backend_client-1.0.0.dist-info/RECORD
